[
  {
    "RESOURCE_ID": 197296,
    "resource_name": "AKT-DC-FS-01",
    "domain_or_workgroup": "MAXPRO",
    "missing_count": 25,
    "installed_count": 11,
    "superceded_count": 1,
    "LAST_SCAN_TIME": 1777701339041,
    "SCAN_STATUS": 2,
    "LAST_SUCCESSFUL_SCAN": 1777701339041
  },
  {
    "RESOURCE_ID": 228326,
    "resource_name": "MAX-DC-AD-01",
    "domain_or_workgroup": "MAXPRO",
    "missing_count": 15,
    "installed_count": 15,
    "superceded_count": 59,
    "LAST_SCAN_TIME": 1777687194727,
    "SCAN_STATUS": 2,
    "LAST_SUCCESSFUL_SCAN": 1777687194727
  },
  {
    "RESOURCE_ID": 324014,
    "resource_name": "MAX-DC-VDI-001",
    "domain_or_workgroup": "MAXPRO",
    "missing_count": 22,
    "installed_count": 60,
    "superceded_count": 41,
    "LAST_SCAN_TIME": 1777701452682,
    "SCAN_STATUS": 2,
    "LAST_SUCCESSFUL_SCAN": 1777701452682
  },
  {
    "RESOURCE_ID": 324015,
    "resource_name": "MAX-DC-VDI-002",
    "domain_or_workgroup": "MAXPRO",
    "missing_count": 22,
    "installed_count": 52,
    "superceded_count": 38,
    "LAST_SCAN_TIME": 1777702022479,
    "SCAN_STATUS": 2,
    "LAST_SUCCESSFUL_SCAN": 1777702022479
  },
  {
    "RESOURCE_ID": 166904,
    "resource_name": "MAX-DC-VDI-GI",
    "domain_or_workgroup": "MAXPRO",
    "missing_count": 24,
    "installed_count": 56,
    "superceded_count": 161,
    "LAST_SCAN_TIME": 1777702456690,
    "SCAN_STATUS": 2,
    "LAST_SUCCESSFUL_SCAN": 1777702456690
  }
]