[
  {
    "RESOURCE_ID": 321934,
    "resource_name": "Alex-DisruptiX",
    "PATCH_ID": 112861,
    "PATCHNAME": "VC_redist.x86__14.50.35719.0.exe",
    "BULLETINID": "MSWU-3550",
    "SEVERITYID": 0,
    "DEPLOY_STATUS": 2,
    "DEPLOY_STATUS_ID": 209,
    "INSTALLED_TIME": 1777083178000,
    "ERROR_CODE": -1,
    "status_updated_time": 1777083193731,
    "REMARKS": "The operation completed successfully. "
  },
  {
    "RESOURCE_ID": 321934,
    "resource_name": "Alex-DisruptiX",
    "PATCH_ID": 44187,
    "PATCHNAME": "Office365_installer_19929.20090B_currentx64.exe",
    "BULLETINID": "MS21-O365C",
    "SEVERITYID": 0,
    "DEPLOY_STATUS": 2,
    "DEPLOY_STATUS_ID": 209,
    "INSTALLED_TIME": 1777079179000,
    "ERROR_CODE": -1,
    "status_updated_time": 1777080334012,
    "REMARKS": "The operation completed successfully. "
  },
  {
    "RESOURCE_ID": 321934,
    "resource_name": "Alex-DisruptiX",
    "PATCH_ID": 44036,
    "PATCHNAME": "windows-kb890830-x64-v5.140.exe",
    "BULLETINID": "MSRT-001",
    "SEVERITYID": 2,
    "DEPLOY_STATUS": 2,
    "DEPLOY_STATUS_ID": 209,
    "INSTALLED_TIME": 1776475311000,
    "ERROR_CODE": -1,
    "status_updated_time": 1776475646561,
    "REMARKS": "The operation completed successfully. "
  },
  {
    "RESOURCE_ID": 321934,
    "resource_name": "Alex-DisruptiX",
    "PATCH_ID": 44105,
    "PATCHNAME": "Office365_installer_19822.20182B_currentx64.exe",
    "BULLETINID": "MS21-O365C",
    "SEVERITYID": 4,
    "DEPLOY_STATUS": 2,
    "DEPLOY_STATUS_ID": 209,
    "INSTALLED_TIME": 1776474372000,
    "ERROR_CODE": -1,
    "status_updated_time": 1776475311176,
    "REMARKS": "The operation completed successfully. "
  },
  {
    "RESOURCE_ID": 321934,
    "resource_name": "Alex-DisruptiX",
    "PATCH_ID": 357355,
    "PATCHNAME": "cisco-secure-client-win-5.1.16.194-core-vpn-predeploy-k9.msi",
    "BULLETINID": "TU-1462",
    "SEVERITYID": 2,
    "DEPLOY_STATUS": 3,
    "DEPLOY_STATUS_ID": 245,
    "INSTALLED_TIME": 1775877004000,
    "ERROR_CODE": -1,
    "status_updated_time": 1775877005357,
    "REMARKS": "dc.db.agent.patchinstall.download_expired"
  },
  {
    "RESOURCE_ID": 321934,
    "resource_name": "Alex-DisruptiX",
    "PATCH_ID": 113144,
    "PATCHNAME": "windows11.0-kb5086672-arm64-25H2_win11.msu",
    "BULLETINID": "MSWU-3706",
    "SEVERITYID": 0,
    "DEPLOY_STATUS": 2,
    "DEPLOY_STATUS_ID": 209,
    "INSTALLED_TIME": 1775875937000,
    "ERROR_CODE": -1,
    "status_updated_time": 1775876968337,
    "REMARKS": "dc.db.agent.config.patchscan.success"
  },
  {
    "RESOURCE_ID": 321934,
    "resource_name": "Alex-DisruptiX",
    "PATCH_ID": 43976,
    "PATCHNAME": "Office365_installer_19822.20168B_currentx64.exe",
    "BULLETINID": "MS21-O365C",
    "SEVERITYID": 0,
    "DEPLOY_STATUS": 2,
    "DEPLOY_STATUS_ID": 209,
    "INSTALLED_TIME": 1775875132000,
    "ERROR_CODE": -1,
    "status_updated_time": 1775875940013,
    "REMARKS": "The operation completed successfully. "
  },
  {
    "RESOURCE_ID": 321934,
    "resource_name": "Alex-DisruptiX",
    "PATCH_ID": 43720,
    "PATCHNAME": "Office365_installer_19725.20190B_currentx64.exe",
    "BULLETINID": "MS21-O365C",
    "SEVERITYID": 0,
    "DEPLOY_STATUS": 2,
    "DEPLOY_STATUS_ID": 209,
    "INSTALLED_TIME": 1774141564000,
    "ERROR_CODE": -1,
    "status_updated_time": 1774142344891,
    "REMARKS": "The operation completed successfully. "
  },
  {
    "RESOURCE_ID": 321934,
    "resource_name": "Alex-DisruptiX",
    "PATCH_ID": 356917,
    "PATCHNAME": "ZoomInstallerFull_6.7.8.32670_64.exe",
    "BULLETINID": "TU-1665",
    "SEVERITYID": 2,
    "DEPLOY_STATUS": 2,
    "DEPLOY_STATUS_ID": 209,
    "INSTALLED_TIME": 1773451691000,
    "ERROR_CODE": -1,
    "status_updated_time": 1773451724797,
    "REMARKS": "The operation completed successfully. "
  },
  {
    "RESOURCE_ID": 321934,
    "resource_name": "Alex-DisruptiX",
    "PATCH_ID": 43626,
    "PATCHNAME": "Office365_installer_19725.20172B_currentx64.exe",
    "BULLETINID": "MS21-O365C",
    "SEVERITYID": 4,
    "DEPLOY_STATUS": 2,
    "DEPLOY_STATUS_ID": 209,
    "INSTALLED_TIME": 1773450366000,
    "ERROR_CODE": -1,
    "status_updated_time": 1773451691060,
    "REMARKS": "The operation completed successfully. "
  },
  {
    "RESOURCE_ID": 321934,
    "resource_name": "Alex-DisruptiX",
    "PATCH_ID": 356586,
    "PATCHNAME": "cisco-secure-client-win-5.1.15.287-core-vpn-predeploy-k9.msi",
    "BULLETINID": "TU-1462",
    "SEVERITYID": 2,
    "DEPLOY_STATUS": 3,
    "DEPLOY_STATUS_ID": 245,
    "INSTALLED_TIME": 1772851780000,
    "ERROR_CODE": -1,
    "status_updated_time": 1772851781539,
    "REMARKS": "dc.db.agent.patchinstall.download_expired"
  },
  {
    "RESOURCE_ID": 321934,
    "resource_name": "Alex-DisruptiX",
    "PATCH_ID": 43547,
    "PATCHNAME": "Office365_installer_19725.20152B_currentx64.exe",
    "BULLETINID": "MS21-O365C",
    "SEVERITYID": 0,
    "DEPLOY_STATUS": 2,
    "DEPLOY_STATUS_ID": 209,
    "INSTALLED_TIME": 1772850269000,
    "ERROR_CODE": -1,
    "status_updated_time": 1772851665710,
    "REMARKS": "The operation completed successfully. "
  },
  {
    "RESOURCE_ID": 321934,
    "resource_name": "Alex-DisruptiX",
    "PATCH_ID": 356373,
    "PATCHNAME": "revosetup_2.6.8.exe",
    "BULLETINID": "TU-1381",
    "SEVERITYID": 2,
    "DEPLOY_STATUS": 2,
    "DEPLOY_STATUS_ID": 209,
    "INSTALLED_TIME": 1772246458000,
    "ERROR_CODE": -1,
    "status_updated_time": 1772246471796,
    "REMARKS": "The operation completed successfully. "
  },
  {
    "RESOURCE_ID": 321934,
    "resource_name": "Alex-DisruptiX",
    "PATCH_ID": 113062,
    "PATCHNAME": "windows11.0-kb5077241-arm64-25H2_win11.msu",
    "BULLETINID": "MSWU-3702",
    "SEVERITYID": 0,
    "DEPLOY_STATUS": 2,
    "DEPLOY_STATUS_ID": 209,
    "INSTALLED_TIME": 1772245595000,
    "ERROR_CODE": -1,
    "status_updated_time": 1772246458253,
    "REMARKS": "dc.db.agent.config.patchscan.success"
  },
  {
    "RESOURCE_ID": 321934,
    "resource_name": "Alex-DisruptiX",
    "PATCH_ID": 43527,
    "PATCHNAME": "Office365_installer_19725.20126B_currentx64.exe",
    "BULLETINID": "MS21-O365C",
    "SEVERITYID": 0,
    "DEPLOY_STATUS": 2,
    "DEPLOY_STATUS_ID": 209,
    "INSTALLED_TIME": 1772244373000,
    "ERROR_CODE": -1,
    "status_updated_time": 1772245595342,
    "REMARKS": "The operation completed successfully. "
  },
  {
    "RESOURCE_ID": 321934,
    "resource_name": "Alex-DisruptiX",
    "PATCH_ID": 355940,
    "PATCHNAME": "ZoomInstallerFull_6.7.5.30439_64.exe",
    "BULLETINID": "TU-1665",
    "SEVERITYID": 2,
    "DEPLOY_STATUS": 2,
    "DEPLOY_STATUS_ID": 209,
    "INSTALLED_TIME": 1771036341000,
    "ERROR_CODE": -1,
    "status_updated_time": 1771036375417,
    "REMARKS": "The operation completed successfully. "
  },
  {
    "RESOURCE_ID": 321934,
    "resource_name": "Alex-DisruptiX",
    "PATCH_ID": 355686,
    "PATCHNAME": "shotcut-win64-26.1.30.exe",
    "BULLETINID": "TU-1350",
    "SEVERITYID": 2,
    "DEPLOY_STATUS": 2,
    "DEPLOY_STATUS_ID": 209,
    "INSTALLED_TIME": 1771036238000,
    "ERROR_CODE": -1,
    "status_updated_time": 1771036341279,
    "REMARKS": "The operation completed successfully. "
  },
  {
    "RESOURCE_ID": 321934,
    "resource_name": "Alex-DisruptiX",
    "PATCH_ID": 113010,
    "PATCHNAME": "windows11.0-kb5074828-arm64-ndp481-25H2_win11.msu",
    "BULLETINID": "MSWU-3699",
    "SEVERITYID": 0,
    "DEPLOY_STATUS": 2,
    "DEPLOY_STATUS_ID": 209,
    "INSTALLED_TIME": 1771036153000,
    "ERROR_CODE": -1,
    "status_updated_time": 1771036238754,
    "REMARKS": "dc.db.agent.config.patchscan.success"
  },
  {
    "RESOURCE_ID": 321934,
    "resource_name": "Alex-DisruptiX",
    "PATCH_ID": 43455,
    "PATCHNAME": "Office365_installer_19628.20204B_currentx64.exe",
    "BULLETINID": "MS21-O365C",
    "SEVERITYID": 3,
    "DEPLOY_STATUS": 2,
    "DEPLOY_STATUS_ID": 209,
    "INSTALLED_TIME": 1771034775000,
    "ERROR_CODE": -1,
    "status_updated_time": 1771036002322,
    "REMARKS": "The operation completed successfully. "
  },
  {
    "RESOURCE_ID": 321934,
    "resource_name": "Alex-DisruptiX",
    "PATCH_ID": 112988,
    "PATCHNAME": "windows11.0-kb5078127-arm64-25H2_win11.msu",
    "BULLETINID": "MSWU-3695",
    "SEVERITYID": 0,
    "DEPLOY_STATUS": 2,
    "DEPLOY_STATUS_ID": 209,
    "INSTALLED_TIME": 1769830619000,
    "ERROR_CODE": -1,
    "status_updated_time": 1769831135716,
    "REMARKS": "dc.db.agent.config.patchscan.success"
  },
  {
    "RESOURCE_ID": 321934,
    "resource_name": "Alex-DisruptiX",
    "PATCH_ID": 43354,
    "PATCHNAME": "Office365_installer_19628.20150_currentx64.exe",
    "BULLETINID": "MS21-O365C",
    "SEVERITYID": 3,
    "DEPLOY_STATUS": 2,
    "DEPLOY_STATUS_ID": 209,
    "INSTALLED_TIME": 1769825167000,
    "ERROR_CODE": -1,
    "status_updated_time": 1769830619176,
    "REMARKS": "The operation completed successfully. "
  },
  {
    "RESOURCE_ID": 321934,
    "resource_name": "Alex-DisruptiX",
    "PATCH_ID": 112956,
    "PATCHNAME": "windows11.0-kb5077744-arm64-25H2_win11.msu",
    "BULLETINID": "MSWU-3695",
    "SEVERITYID": 0,
    "DEPLOY_STATUS": 2,
    "DEPLOY_STATUS_ID": 209,
    "INSTALLED_TIME": 1769220368000,
    "ERROR_CODE": -1,
    "status_updated_time": 1769220998892,
    "REMARKS": "dc.db.agent.config.patchscan.success"
  },
  {
    "RESOURCE_ID": 321934,
    "resource_name": "Alex-DisruptiX",
    "PATCH_ID": 43278,
    "PATCHNAME": "Office365_installer_19530.20144_currentx64.exe",
    "BULLETINID": "MS21-O365C",
    "SEVERITYID": 4,
    "DEPLOY_STATUS": 2,
    "DEPLOY_STATUS_ID": 209,
    "INSTALLED_TIME": 1768615568000,
    "ERROR_CODE": -1,
    "status_updated_time": 1768617433898,
    "REMARKS": "The operation completed successfully. "
  },
  {
    "RESOURCE_ID": 321934,
    "resource_name": "Alex-DisruptiX",
    "PATCH_ID": 354762,
    "PATCHNAME": "shotcut-win64-25.12.31.exe",
    "BULLETINID": "TU-1350",
    "SEVERITYID": 2,
    "DEPLOY_STATUS": 2,
    "DEPLOY_STATUS_ID": 209,
    "INSTALLED_TIME": 1768010754000,
    "ERROR_CODE": -1,
    "status_updated_time": 1768010869064,
    "REMARKS": "The operation completed successfully. "
  },
  {
    "RESOURCE_ID": 321934,
    "resource_name": "Alex-DisruptiX",
    "PATCH_ID": 354691,
    "PATCHNAME": "ZoomInstallerFull_6.7.2.26346_64.exe",
    "BULLETINID": "TU-1665",
    "SEVERITYID": 2,
    "DEPLOY_STATUS": 2,
    "DEPLOY_STATUS_ID": 209,
    "INSTALLED_TIME": 1767407301000,
    "ERROR_CODE": -1,
    "status_updated_time": 1767407335982,
    "REMARKS": "The operation completed successfully. "
  },
  {
    "RESOURCE_ID": 321934,
    "resource_name": "Alex-DisruptiX",
    "PATCH_ID": 354197,
    "PATCHNAME": "audacity-win-3.7.7-32bit.exe",
    "BULLETINID": "TU-061",
    "SEVERITYID": 2,
    "DEPLOY_STATUS": 2,
    "DEPLOY_STATUS_ID": 209,
    "INSTALLED_TIME": 1767407281000,
    "ERROR_CODE": -1,
    "status_updated_time": 1767407299942,
    "REMARKS": "The operation completed successfully. "
  },
  {
    "RESOURCE_ID": 321934,
    "resource_name": "Alex-DisruptiX",
    "PATCH_ID": 354131,
    "PATCHNAME": "revosetup_2.6.5.exe",
    "BULLETINID": "TU-1381",
    "SEVERITYID": 2,
    "DEPLOY_STATUS": 2,
    "DEPLOY_STATUS_ID": 209,
    "INSTALLED_TIME": 1767407268000,
    "ERROR_CODE": -1,
    "status_updated_time": 1767407280693,
    "REMARKS": "The operation completed successfully. "
  },
  {
    "RESOURCE_ID": 321934,
    "resource_name": "Alex-DisruptiX",
    "PATCH_ID": 43169,
    "PATCHNAME": "Office365_installer_19426.20218_currentx64.exe",
    "BULLETINID": "MS21-O365C",
    "SEVERITYID": 0,
    "DEPLOY_STATUS": 2,
    "DEPLOY_STATUS_ID": 209,
    "INSTALLED_TIME": 1767405962000,
    "ERROR_CODE": -1,
    "status_updated_time": 1767407090772,
    "REMARKS": "The operation completed successfully. "
  },
  {
    "RESOURCE_ID": 321934,
    "resource_name": "Alex-DisruptiX",
    "PATCH_ID": 353970,
    "PATCHNAME": "audacity-win-3.7.6-32bit.exe",
    "BULLETINID": "TU-061",
    "SEVERITYID": 2,
    "DEPLOY_STATUS": 2,
    "DEPLOY_STATUS_ID": 209,
    "INSTALLED_TIME": 1764994108000,
    "ERROR_CODE": -1,
    "status_updated_time": 1764994272360,
    "REMARKS": "The operation completed successfully. "
  },
  {
    "RESOURCE_ID": 321934,
    "resource_name": "Alex-DisruptiX",
    "PATCH_ID": 353810,
    "PATCHNAME": "cisco-secure-client-win-5.1.13.177-core-vpn-predeploy-k9.msi",
    "BULLETINID": "TU-1462",
    "SEVERITYID": 2,
    "DEPLOY_STATUS": 3,
    "DEPLOY_STATUS_ID": 245,
    "INSTALLED_TIME": 1764988011000,
    "ERROR_CODE": -1,
    "status_updated_time": 1764988013770,
    "REMARKS": "dc.db.agent.patchinstall.download_expired"
  },
  {
    "RESOURCE_ID": 321934,
    "resource_name": "Alex-DisruptiX",
    "PATCH_ID": 112862,
    "PATCHNAME": "VC_redist.x64__14.50.35719.0.exe",
    "BULLETINID": "MSWU-3550",
    "SEVERITYID": 0,
    "DEPLOY_STATUS": 2,
    "DEPLOY_STATUS_ID": 209,
    "INSTALLED_TIME": 1764986929000,
    "ERROR_CODE": -1,
    "status_updated_time": 1764986976268,
    "REMARKS": "dc.db.agent.config.patchscan.success"
  },
  {
    "RESOURCE_ID": 321937,
    "resource_name": "DESKTOP-AI6612F",
    "PATCH_ID": 357355,
    "PATCHNAME": "cisco-secure-client-win-5.1.16.194-core-vpn-predeploy-k9.msi",
    "BULLETINID": "TU-1462",
    "SEVERITYID": 2,
    "DEPLOY_STATUS": 3,
    "DEPLOY_STATUS_ID": 245,
    "INSTALLED_TIME": 1776582839000,
    "ERROR_CODE": -1,
    "status_updated_time": 1776582842113,
    "REMARKS": "dc.db.agent.patchinstall.download_expired"
  },
  {
    "RESOURCE_ID": 321937,
    "resource_name": "DESKTOP-AI6612F",
    "PATCH_ID": 357798,
    "PATCHNAME": "ZoomInstallerFull_7.0.2.34412_64.exe",
    "BULLETINID": "TU-1665",
    "SEVERITYID": 3,
    "DEPLOY_STATUS": 2,
    "DEPLOY_STATUS_ID": 209,
    "INSTALLED_TIME": 1776582700000,
    "ERROR_CODE": -1,
    "status_updated_time": 1776582764653,
    "REMARKS": "The operation completed successfully. "
  },
  {
    "RESOURCE_ID": 321937,
    "resource_name": "DESKTOP-AI6612F",
    "PATCH_ID": 113375,
    "PATCHNAME": "MicrosoftEdgeWebView2RuntimeInstallerX64_147.0.3912.72.exe",
    "BULLETINID": "MSWU-3507",
    "SEVERITYID": 0,
    "DEPLOY_STATUS": 2,
    "DEPLOY_STATUS_ID": 209,
    "INSTALLED_TIME": 1776582618000,
    "ERROR_CODE": -1,
    "status_updated_time": 1776582700734,
    "REMARKS": "The operation completed successfully. "
  },
  {
    "RESOURCE_ID": 321937,
    "resource_name": "DESKTOP-AI6612F",
    "PATCH_ID": 44173,
    "PATCHNAME": "microsoftedgeenterprise_147.0.3912.72_x64.msi",
    "BULLETINID": "MS22-EDGE",
    "SEVERITYID": 4,
    "DEPLOY_STATUS": 2,
    "DEPLOY_STATUS_ID": 209,
    "INSTALLED_TIME": 1776582465000,
    "ERROR_CODE": -1,
    "status_updated_time": 1776582618636,
    "REMARKS": "The operation completed successfully. "
  },
  {
    "RESOURCE_ID": 321937,
    "resource_name": "DESKTOP-AI6612F",
    "PATCH_ID": 44062,
    "PATCHNAME": "windowsdesktop-runtime-8.0.26-win-x64.exe",
    "BULLETINID": "MS26-DOTNET",
    "SEVERITYID": 3,
    "DEPLOY_STATUS": 2,
    "DEPLOY_STATUS_ID": 209,
    "INSTALLED_TIME": 1776582398000,
    "ERROR_CODE": -1,
    "status_updated_time": 1776582465264,
    "REMARKS": "dc.db.agent.config.patchscan.success"
  },
  {
    "RESOURCE_ID": 321937,
    "resource_name": "DESKTOP-AI6612F",
    "PATCH_ID": 44055,
    "PATCHNAME": "windows11.0-kb5083769-x64-25H2_win11.msu",
    "BULLETINID": "MS26-APR3",
    "SEVERITYID": 4,
    "DEPLOY_STATUS": 2,
    "DEPLOY_STATUS_ID": 209,
    "INSTALLED_TIME": 1776581611000,
    "ERROR_CODE": -1,
    "status_updated_time": 1776582398410,
    "REMARKS": "dc.db.agent.config.patchscan.success"
  },
  {
    "RESOURCE_ID": 321937,
    "resource_name": "DESKTOP-AI6612F",
    "PATCH_ID": 44010,
    "PATCHNAME": "windows11.0-kb5082417-x64-ndp481-25H2_win11.msu",
    "BULLETINID": "MS26-APR12",
    "SEVERITYID": 4,
    "DEPLOY_STATUS": 2,
    "DEPLOY_STATUS_ID": 209,
    "INSTALLED_TIME": 1776581547000,
    "ERROR_CODE": -1,
    "status_updated_time": 1776581611343,
    "REMARKS": "dc.db.agent.config.patchscan.success"
  },
  {
    "RESOURCE_ID": 321937,
    "resource_name": "DESKTOP-AI6612F",
    "PATCH_ID": 44109,
    "PATCHNAME": "Office365_installer_19822.20182_currentx64.exe",
    "BULLETINID": "MS21-O365C",
    "SEVERITYID": 4,
    "DEPLOY_STATUS": 2,
    "DEPLOY_STATUS_ID": 209,
    "INSTALLED_TIME": 1776571565000,
    "ERROR_CODE": -1,
    "status_updated_time": 1776581547405,
    "REMARKS": "The operation completed successfully. "
  },
  {
    "RESOURCE_ID": 321937,
    "resource_name": "DESKTOP-AI6612F",
    "PATCH_ID": 356586,
    "PATCHNAME": "cisco-secure-client-win-5.1.15.287-core-vpn-predeploy-k9.msi",
    "BULLETINID": "TU-1462",
    "SEVERITYID": 2,
    "DEPLOY_STATUS": 3,
    "DEPLOY_STATUS_ID": 245,
    "INSTALLED_TIME": 1774168472000,
    "ERROR_CODE": -1,
    "status_updated_time": 1774168472185,
    "REMARKS": "dc.db.agent.patchinstall.download_expired"
  },
  {
    "RESOURCE_ID": 321937,
    "resource_name": "DESKTOP-AI6612F",
    "PATCH_ID": 113009,
    "PATCHNAME": "windows11.0-kb5074828-x64-ndp481-25H2_win11.msu",
    "BULLETINID": "MSWU-3699",
    "SEVERITYID": 0,
    "DEPLOY_STATUS": 2,
    "DEPLOY_STATUS_ID": 209,
    "INSTALLED_TIME": 1774168119000,
    "ERROR_CODE": -1,
    "status_updated_time": 1774168429080,
    "REMARKS": "dc.db.agent.config.patchscan.success"
  },
  {
    "RESOURCE_ID": 321937,
    "resource_name": "DESKTOP-AI6612F",
    "PATCH_ID": 43736,
    "PATCHNAME": "microsoftedgeenterprise_146.0.3856.72_x64.msi",
    "BULLETINID": "MS22-EDGE",
    "SEVERITYID": 4,
    "DEPLOY_STATUS": 2,
    "DEPLOY_STATUS_ID": 209,
    "INSTALLED_TIME": 1774167948000,
    "ERROR_CODE": -1,
    "status_updated_time": 1774168117846,
    "REMARKS": "The operation completed successfully. "
  },
  {
    "RESOURCE_ID": 321937,
    "resource_name": "DESKTOP-AI6612F",
    "PATCH_ID": 43606,
    "PATCHNAME": "windowsdesktop-runtime-8.0.25-win-x64.exe",
    "BULLETINID": "MS26-DOTNET",
    "SEVERITYID": 3,
    "DEPLOY_STATUS": 2,
    "DEPLOY_STATUS_ID": 209,
    "INSTALLED_TIME": 1774167856000,
    "ERROR_CODE": -1,
    "status_updated_time": 1774167946698,
    "REMARKS": "dc.db.agent.config.patchscan.success"
  },
  {
    "RESOURCE_ID": 321937,
    "resource_name": "DESKTOP-AI6612F",
    "PATCH_ID": 43586,
    "PATCHNAME": "windows11.0-kb5079473-x64-25H2_win11.msu",
    "BULLETINID": "MS26-MAR3",
    "SEVERITYID": 4,
    "DEPLOY_STATUS": 2,
    "DEPLOY_STATUS_ID": 209,
    "INSTALLED_TIME": 1774166985000,
    "ERROR_CODE": -1,
    "status_updated_time": 1774167854321,
    "REMARKS": "dc.db.agent.config.patchscan.success"
  },
  {
    "RESOURCE_ID": 321937,
    "resource_name": "DESKTOP-AI6612F",
    "PATCH_ID": 43724,
    "PATCHNAME": "Office365_installer_19725.20190_currentx64.exe",
    "BULLETINID": "MS21-O365C",
    "SEVERITYID": 0,
    "DEPLOY_STATUS": 2,
    "DEPLOY_STATUS_ID": 209,
    "INSTALLED_TIME": 1774164166000,
    "ERROR_CODE": -1,
    "status_updated_time": 1774166983206,
    "REMARKS": "The operation completed successfully. "
  },
  {
    "RESOURCE_ID": 321937,
    "resource_name": "DESKTOP-AI6612F",
    "PATCH_ID": 353810,
    "PATCHNAME": "cisco-secure-client-win-5.1.13.177-core-vpn-predeploy-k9.msi",
    "BULLETINID": "TU-1462",
    "SEVERITYID": 2,
    "DEPLOY_STATUS": 3,
    "DEPLOY_STATUS_ID": 245,
    "INSTALLED_TIME": 1766825856000,
    "ERROR_CODE": -1,
    "status_updated_time": 1766825856229,
    "REMARKS": "dc.db.agent.patchinstall.download_expired"
  },
  {
    "RESOURCE_ID": 321937,
    "resource_name": "DESKTOP-AI6612F",
    "PATCH_ID": 112862,
    "PATCHNAME": "VC_redist.x64__14.50.35719.0.exe",
    "BULLETINID": "MSWU-3550",
    "SEVERITYID": 0,
    "DEPLOY_STATUS": 2,
    "DEPLOY_STATUS_ID": 209,
    "INSTALLED_TIME": 1766825725000,
    "ERROR_CODE": -1,
    "status_updated_time": 1766825752301,
    "REMARKS": "The operation completed successfully. "
  },
  {
    "RESOURCE_ID": 321937,
    "resource_name": "DESKTOP-AI6612F",
    "PATCH_ID": 112861,
    "PATCHNAME": "VC_redist.x86__14.50.35719.0.exe",
    "BULLETINID": "MSWU-3550",
    "SEVERITYID": 0,
    "DEPLOY_STATUS": 2,
    "DEPLOY_STATUS_ID": 209,
    "INSTALLED_TIME": 1766825704000,
    "ERROR_CODE": -1,
    "status_updated_time": 1766825723592,
    "REMARKS": "The operation completed successfully. "
  },
  {
    "RESOURCE_ID": 321937,
    "resource_name": "DESKTOP-AI6612F",
    "PATCH_ID": 43169,
    "PATCHNAME": "Office365_installer_19426.20218_currentx64.exe",
    "BULLETINID": "MS21-O365C",
    "SEVERITYID": 0,
    "DEPLOY_STATUS": 2,
    "DEPLOY_STATUS_ID": 209,
    "INSTALLED_TIME": 1766823806000,
    "ERROR_CODE": -1,
    "status_updated_time": 1766825642667,
    "REMARKS": "The operation completed successfully. "
  },
  {
    "RESOURCE_ID": 321927,
    "resource_name": "Jen",
    "PATCH_ID": 357355,
    "PATCHNAME": "cisco-secure-client-win-5.1.16.194-core-vpn-predeploy-k9.msi",
    "BULLETINID": "TU-1462",
    "SEVERITYID": 2,
    "DEPLOY_STATUS": 3,
    "DEPLOY_STATUS_ID": 245,
    "INSTALLED_TIME": 1774717475000,
    "ERROR_CODE": -1,
    "status_updated_time": 1774717475949,
    "REMARKS": "dc.db.agent.patchinstall.download_expired"
  },
  {
    "RESOURCE_ID": 321927,
    "resource_name": "Jen",
    "PATCH_ID": 43738,
    "PATCHNAME": "Office365_installer_19822.20114B_currentx64.exe",
    "BULLETINID": "MS21-O365C",
    "SEVERITYID": 0,
    "DEPLOY_STATUS": 2,
    "DEPLOY_STATUS_ID": 209,
    "INSTALLED_TIME": 1774675254000,
    "ERROR_CODE": -1,
    "status_updated_time": 1774717474669,
    "REMARKS": "The operation completed successfully. "
  },
  {
    "RESOURCE_ID": 321927,
    "resource_name": "Jen",
    "PATCH_ID": 356586,
    "PATCHNAME": "cisco-secure-client-win-5.1.15.287-core-vpn-predeploy-k9.msi",
    "BULLETINID": "TU-1462",
    "SEVERITYID": 2,
    "DEPLOY_STATUS": 3,
    "DEPLOY_STATUS_ID": 245,
    "INSTALLED_TIME": 1772968731000,
    "ERROR_CODE": -1,
    "status_updated_time": 1772970361632,
    "REMARKS": "dc.db.agent.patchinstall.download_expired"
  },
  {
    "RESOURCE_ID": 321927,
    "resource_name": "Jen",
    "PATCH_ID": 112862,
    "PATCHNAME": "VC_redist.x64__14.50.35719.0.exe",
    "BULLETINID": "MSWU-3550",
    "SEVERITYID": 0,
    "DEPLOY_STATUS": 2,
    "DEPLOY_STATUS_ID": 209,
    "INSTALLED_TIME": 1772963124000,
    "ERROR_CODE": -1,
    "status_updated_time": 1772968729676,
    "REMARKS": "dc.db.agent.config.patchscan.success"
  },
  {
    "RESOURCE_ID": 321927,
    "resource_name": "Jen",
    "PATCH_ID": 112861,
    "PATCHNAME": "VC_redist.x86__14.50.35719.0.exe",
    "BULLETINID": "MSWU-3550",
    "SEVERITYID": 0,
    "DEPLOY_STATUS": 2,
    "DEPLOY_STATUS_ID": 209,
    "INSTALLED_TIME": 1772963103000,
    "ERROR_CODE": -1,
    "status_updated_time": 1772963123682,
    "REMARKS": "The operation completed successfully. "
  },
  {
    "RESOURCE_ID": 321927,
    "resource_name": "Jen",
    "PATCH_ID": 43547,
    "PATCHNAME": "Office365_installer_19725.20152B_currentx64.exe",
    "BULLETINID": "MS21-O365C",
    "SEVERITYID": 0,
    "DEPLOY_STATUS": 2,
    "DEPLOY_STATUS_ID": 209,
    "INSTALLED_TIME": 1772954487000,
    "ERROR_CODE": -1,
    "status_updated_time": 1772963102895,
    "REMARKS": "The operation completed successfully. "
  },
  {
    "RESOURCE_ID": 321927,
    "resource_name": "Jen",
    "PATCH_ID": 43527,
    "PATCHNAME": "Office365_installer_19725.20126B_currentx64.exe",
    "BULLETINID": "MS21-O365C",
    "SEVERITYID": 0,
    "DEPLOY_STATUS": 2,
    "DEPLOY_STATUS_ID": 209,
    "INSTALLED_TIME": 1772342455000,
    "ERROR_CODE": -1,
    "status_updated_time": 1772393976101,
    "REMARKS": "The operation completed successfully. "
  },
  {
    "RESOURCE_ID": 321927,
    "resource_name": "Jen",
    "PATCH_ID": 43354,
    "PATCHNAME": "Office365_installer_19628.20150_currentx64.exe",
    "BULLETINID": "MS21-O365C",
    "SEVERITYID": 3,
    "DEPLOY_STATUS": 2,
    "DEPLOY_STATUS_ID": 209,
    "INSTALLED_TIME": 1769922295000,
    "ERROR_CODE": -1,
    "status_updated_time": 1769951335290,
    "REMARKS": "The operation completed successfully. "
  },
  {
    "RESOURCE_ID": 321927,
    "resource_name": "Jen",
    "PATCH_ID": 43169,
    "PATCHNAME": "Office365_installer_19426.20218_currentx64.exe",
    "BULLETINID": "MS21-O365C",
    "SEVERITYID": 0,
    "DEPLOY_STATUS": 2,
    "DEPLOY_STATUS_ID": 209,
    "INSTALLED_TIME": 1767513702000,
    "ERROR_CODE": -1,
    "status_updated_time": 1767534601797,
    "REMARKS": "The operation completed successfully. "
  },
  {
    "RESOURCE_ID": 321927,
    "resource_name": "Jen",
    "PATCH_ID": 353810,
    "PATCHNAME": "cisco-secure-client-win-5.1.13.177-core-vpn-predeploy-k9.msi",
    "BULLETINID": "TU-1462",
    "SEVERITYID": 2,
    "DEPLOY_STATUS": 3,
    "DEPLOY_STATUS_ID": 245,
    "INSTALLED_TIME": 1765623806000,
    "ERROR_CODE": -1,
    "status_updated_time": 1765642205343,
    "REMARKS": "dc.db.agent.patchinstall.download_expired"
  },
  {
    "RESOURCE_ID": 321931,
    "resource_name": "Miller-Computer",
    "PATCH_ID": 353810,
    "PATCHNAME": "cisco-secure-client-win-5.1.13.177-core-vpn-predeploy-k9.msi",
    "BULLETINID": "TU-1462",
    "SEVERITYID": 2,
    "DEPLOY_STATUS": 3,
    "DEPLOY_STATUS_ID": 245,
    "INSTALLED_TIME": 1769319307000,
    "ERROR_CODE": -1,
    "status_updated_time": 1769319306174,
    "REMARKS": "dc.db.agent.patchinstall.download_expired"
  },
  {
    "RESOURCE_ID": 321931,
    "resource_name": "Miller-Computer",
    "PATCH_ID": 354691,
    "PATCHNAME": "ZoomInstallerFull_6.7.2.26346_64.exe",
    "BULLETINID": "TU-1665",
    "SEVERITYID": 2,
    "DEPLOY_STATUS": 2,
    "DEPLOY_STATUS_ID": 209,
    "INSTALLED_TIME": 1769319236000,
    "ERROR_CODE": -1,
    "status_updated_time": 1769319271683,
    "REMARKS": "The operation completed successfully. "
  },
  {
    "RESOURCE_ID": 321931,
    "resource_name": "Miller-Computer",
    "PATCH_ID": 350357,
    "PATCHNAME": "Dell-Pair-Application_97PXN_WIN64_1.2.8_A00.EXE",
    "BULLETINID": "TU-2011",
    "SEVERITYID": 2,
    "DEPLOY_STATUS": 3,
    "DEPLOY_STATUS_ID": 245,
    "INSTALLED_TIME": 1769319234000,
    "ERROR_CODE": 8,
    "status_updated_time": 1769319271683,
    "REMARKS": "Patch update delayed since application is used by another process."
  },
  {
    "RESOURCE_ID": 321931,
    "resource_name": "Miller-Computer",
    "PATCH_ID": 112862,
    "PATCHNAME": "VC_redist.x64__14.50.35719.0.exe",
    "BULLETINID": "MSWU-3550",
    "SEVERITYID": 0,
    "DEPLOY_STATUS": 2,
    "DEPLOY_STATUS_ID": 209,
    "INSTALLED_TIME": 1769317813000,
    "ERROR_CODE": -1,
    "status_updated_time": 1769317874708,
    "REMARKS": "dc.db.agent.config.patchscan.success"
  },
  {
    "RESOURCE_ID": 321931,
    "resource_name": "Miller-Computer",
    "PATCH_ID": 43244,
    "PATCHNAME": "windowsdesktop-runtime-9.0.12-win-x64.exe",
    "BULLETINID": "MS23-DOTNET",
    "SEVERITYID": 2,
    "DEPLOY_STATUS": 2,
    "DEPLOY_STATUS_ID": 209,
    "INSTALLED_TIME": 1769317778000,
    "ERROR_CODE": -1,
    "status_updated_time": 1769317811438,
    "REMARKS": "The operation completed successfully. "
  },
  {
    "RESOURCE_ID": 321931,
    "resource_name": "Miller-Computer",
    "PATCH_ID": 43234,
    "PATCHNAME": "windowsdesktop-runtime-8.0.23-win-x86.exe",
    "BULLETINID": "MS23-DOTNET",
    "SEVERITYID": 2,
    "DEPLOY_STATUS": 2,
    "DEPLOY_STATUS_ID": 209,
    "INSTALLED_TIME": 1769317738000,
    "ERROR_CODE": -1,
    "status_updated_time": 1769317775684,
    "REMARKS": "The operation completed successfully. "
  },
  {
    "RESOURCE_ID": 321931,
    "resource_name": "Miller-Computer",
    "PATCH_ID": 43233,
    "PATCHNAME": "windowsdesktop-runtime-8.0.23-win-x64.exe",
    "BULLETINID": "MS23-DOTNET",
    "SEVERITYID": 2,
    "DEPLOY_STATUS": 2,
    "DEPLOY_STATUS_ID": 209,
    "INSTALLED_TIME": 1769317645000,
    "ERROR_CODE": -1,
    "status_updated_time": 1769317736331,
    "REMARKS": "dc.db.agent.config.patchscan.success"
  },
  {
    "RESOURCE_ID": 321931,
    "resource_name": "Miller-Computer",
    "PATCH_ID": 43231,
    "PATCHNAME": "aspnetcore-runtime-8.0.23-win-x64.exe",
    "BULLETINID": "MS23-DOTNET",
    "SEVERITYID": 2,
    "DEPLOY_STATUS": 2,
    "DEPLOY_STATUS_ID": 209,
    "INSTALLED_TIME": 1769317633000,
    "ERROR_CODE": -1,
    "status_updated_time": 1769317642965,
    "REMARKS": "The operation completed successfully. "
  },
  {
    "RESOURCE_ID": 321931,
    "resource_name": "Miller-Computer",
    "PATCH_ID": 40196,
    "PATCHNAME": "windowsdesktop-runtime-6.0.36-win-x64.exe",
    "BULLETINID": "MS23-DOTNET",
    "SEVERITYID": 2,
    "DEPLOY_STATUS": 2,
    "DEPLOY_STATUS_ID": 209,
    "INSTALLED_TIME": 1769317599000,
    "ERROR_CODE": -1,
    "status_updated_time": 1769317630680,
    "REMARKS": "The operation completed successfully. "
  }
]