[
  {
    "Title": "Re: RK Website",
    "Requestor": "RK Engineering Group, Inc.",
    "EntryCount": 2,
    "FirstEntry": "2026-02-19",
    "LastEntry": "2026-02-20",
    "TotalHours_NH": 0.0,
    "TotalHours_AH": 0.75,
    "TotalQty": 0.75,
    "Categories": [
      "Datacenter",
      "Domain SSL"
    ],
    "Resources": [
      "A. Bhardwaj"
    ]
  },
  {
    "Title": "Re: RK Website Down",
    "Requestor": "RK Engineering Group, Inc.",
    "EntryCount": 2,
    "FirstEntry": "2025-07-07",
    "LastEntry": "2025-07-10",
    "TotalHours_NH": 0.0,
    "TotalHours_AH": 0.5800000000000001,
    "TotalQty": 0.5800000000000001,
    "Categories": [
      "Domain SSL",
      "Wordpress"
    ],
    "Resources": [
      "M. Kumar"
    ]
  },
  {
    "Title": "Cloudflare Login",
    "Requestor": "RK Engineering Group, Inc.",
    "EntryCount": 1,
    "FirstEntry": "2024-08-23",
    "LastEntry": "2024-08-23",
    "TotalHours_NH": 0.0,
    "TotalHours_AH": 0.3,
    "TotalQty": 0.3,
    "Categories": [
      "User Generated"
    ],
    "Resources": [
      "G. Kumar"
    ]
  },
  {
    "Title": "RK Engineering Group, Inc. Cloudflare",
    "Requestor": "RK Engineering Group, Inc.",
    "EntryCount": 1,
    "FirstEntry": "2024-01-16",
    "LastEntry": "2024-01-16",
    "TotalHours_NH": 0.0,
    "TotalHours_AH": 0.45,
    "TotalQty": 0.45,
    "Categories": [
      "User Generated"
    ],
    "Resources": [
      "S. Kumar"
    ]
  },
  {
    "Title": "Domain is down",
    "Requestor": "rg@rkengineer.com",
    "EntryCount": 1,
    "FirstEntry": "2024-01-15",
    "LastEntry": "2024-01-15",
    "TotalHours_NH": 0.78,
    "TotalHours_AH": 0.0,
    "TotalQty": 0.78,
    "Categories": [
      "User Generated"
    ],
    "Resources": [
      "J. Chou"
    ]
  },
  {
    "Title": "Troubleshoot Website Issue",
    "Requestor": "RK Engineering Group, Inc.",
    "EntryCount": 1,
    "FirstEntry": "2023-05-01",
    "LastEntry": "2023-05-01",
    "TotalHours_NH": 0.42,
    "TotalHours_AH": 0.0,
    "TotalQty": 0.42,
    "Categories": [
      "User Generated"
    ],
    "Resources": [
      "H. Yaghoubi"
    ]
  },
  {
    "Title": "Website updates",
    "Requestor": "RK Engineering Group, Inc.",
    "EntryCount": 9,
    "FirstEntry": "2023-03-01",
    "LastEntry": "2023-04-17",
    "TotalHours_NH": 6.1499999999999995,
    "TotalHours_AH": 0.0,
    "TotalQty": 6.1499999999999995,
    "Categories": [
      "Project Work",
      "Wordpress"
    ],
    "Resources": [
      "J. Chou"
    ]
  },
  {
    "Title": "SSL Cert Deployment",
    "Requestor": "RK Engineering Group, Inc.",
    "EntryCount": 1,
    "FirstEntry": "2023-02-27",
    "LastEntry": "2023-02-27",
    "TotalHours_NH": 0.5,
    "TotalHours_AH": 0.0,
    "TotalQty": 0.5,
    "Categories": [
      "User Generated"
    ],
    "Resources": [
      "A. Graham"
    ]
  }
]