[
  {
    "count": 11813,
    "timestamp": 1775174400000,
    "date": "2026-04-03",
    "time": "00:00:00",
    "counts": {
      "requests": 11813,
      "allowedrequests": 11474,
      "blockedrequests": 339,
      "connectedevents": 0,
      "disconnectedevents": 0
    }
  },
  {
    "count": 8507,
    "timestamp": 1775178000000,
    "date": "2026-04-03",
    "time": "01:00:00",
    "counts": {
      "requests": 8507,
      "allowedrequests": 8276,
      "blockedrequests": 231,
      "connectedevents": 0,
      "disconnectedevents": 0
    }
  },
  {
    "count": 6469,
    "timestamp": 1775181600000,
    "date": "2026-04-03",
    "time": "02:00:00",
    "counts": {
      "requests": 6469,
      "allowedrequests": 6299,
      "blockedrequests": 170,
      "connectedevents": 0,
      "disconnectedevents": 0
    }
  },
  {
    "count": 5839,
    "timestamp": 1775185200000,
    "date": "2026-04-03",
    "time": "03:00:00",
    "counts": {
      "requests": 5839,
      "allowedrequests": 5736,
      "blockedrequests": 103,
      "connectedevents": 0,
      "disconnectedevents": 0
    }
  },
  {
    "count": 5374,
    "timestamp": 1775188800000,
    "date": "2026-04-03",
    "time": "04:00:00",
    "counts": {
      "requests": 5374,
      "allowedrequests": 5283,
      "blockedrequests": 91,
      "connectedevents": 0,
      "disconnectedevents": 0
    }
  },
  {
    "count": 5607,
    "timestamp": 1775192400000,
    "date": "2026-04-03",
    "time": "05:00:00",
    "counts": {
      "requests": 5607,
      "allowedrequests": 5509,
      "blockedrequests": 98,
      "connectedevents": 0,
      "disconnectedevents": 0
    }
  },
  {
    "count": 5493,
    "timestamp": 1775196000000,
    "date": "2026-04-03",
    "time": "06:00:00",
    "counts": {
      "requests": 5493,
      "allowedrequests": 5402,
      "blockedrequests": 91,
      "connectedevents": 0,
      "disconnectedevents": 0
    }
  },
  {
    "count": 5484,
    "timestamp": 1775199600000,
    "date": "2026-04-03",
    "time": "07:00:00",
    "counts": {
      "requests": 5484,
      "allowedrequests": 5385,
      "blockedrequests": 99,
      "connectedevents": 0,
      "disconnectedevents": 0
    }
  },
  {
    "count": 5421,
    "timestamp": 1775203200000,
    "date": "2026-04-03",
    "time": "08:00:00",
    "counts": {
      "requests": 5421,
      "allowedrequests": 5321,
      "blockedrequests": 100,
      "connectedevents": 0,
      "disconnectedevents": 0
    }
  },
  {
    "count": 5031,
    "timestamp": 1775206800000,
    "date": "2026-04-03",
    "time": "09:00:00",
    "counts": {
      "requests": 5031,
      "allowedrequests": 4946,
      "blockedrequests": 85,
      "connectedevents": 0,
      "disconnectedevents": 0
    }
  },
  {
    "count": 5389,
    "timestamp": 1775210400000,
    "date": "2026-04-03",
    "time": "10:00:00",
    "counts": {
      "requests": 5389,
      "allowedrequests": 5292,
      "blockedrequests": 97,
      "connectedevents": 0,
      "disconnectedevents": 0
    }
  },
  {
    "count": 5065,
    "timestamp": 1775214000000,
    "date": "2026-04-03",
    "time": "11:00:00",
    "counts": {
      "requests": 5065,
      "allowedrequests": 4969,
      "blockedrequests": 96,
      "connectedevents": 0,
      "disconnectedevents": 0
    }
  },
  {
    "count": 5008,
    "timestamp": 1775217600000,
    "date": "2026-04-03",
    "time": "12:00:00",
    "counts": {
      "requests": 5008,
      "allowedrequests": 4925,
      "blockedrequests": 83,
      "connectedevents": 0,
      "disconnectedevents": 0
    }
  },
  {
    "count": 5707,
    "timestamp": 1775221200000,
    "date": "2026-04-03",
    "time": "13:00:00",
    "counts": {
      "requests": 5707,
      "allowedrequests": 5605,
      "blockedrequests": 102,
      "connectedevents": 0,
      "disconnectedevents": 0
    }
  },
  {
    "count": 11112,
    "timestamp": 1775224800000,
    "date": "2026-04-03",
    "time": "14:00:00",
    "counts": {
      "requests": 11112,
      "allowedrequests": 10902,
      "blockedrequests": 210,
      "connectedevents": 0,
      "disconnectedevents": 0
    }
  },
  {
    "count": 15965,
    "timestamp": 1775228400000,
    "date": "2026-04-03",
    "time": "15:00:00",
    "counts": {
      "requests": 15965,
      "allowedrequests": 15609,
      "blockedrequests": 356,
      "connectedevents": 0,
      "disconnectedevents": 0
    }
  },
  {
    "count": 19846,
    "timestamp": 1775232000000,
    "date": "2026-04-03",
    "time": "16:00:00",
    "counts": {
      "requests": 19846,
      "allowedrequests": 19391,
      "blockedrequests": 455,
      "connectedevents": 0,
      "disconnectedevents": 0
    }
  },
  {
    "count": 18475,
    "timestamp": 1775235600000,
    "date": "2026-04-03",
    "time": "17:00:00",
    "counts": {
      "requests": 18475,
      "allowedrequests": 18080,
      "blockedrequests": 395,
      "connectedevents": 0,
      "disconnectedevents": 0
    }
  },
  {
    "count": 15631,
    "timestamp": 1775239200000,
    "date": "2026-04-03",
    "time": "18:00:00",
    "counts": {
      "requests": 15631,
      "allowedrequests": 15346,
      "blockedrequests": 285,
      "connectedevents": 0,
      "disconnectedevents": 0
    }
  },
  {
    "count": 15179,
    "timestamp": 1775242800000,
    "date": "2026-04-03",
    "time": "19:00:00",
    "counts": {
      "requests": 15179,
      "allowedrequests": 14847,
      "blockedrequests": 332,
      "connectedevents": 0,
      "disconnectedevents": 0
    }
  },
  {
    "count": 16658,
    "timestamp": 1775246400000,
    "date": "2026-04-03",
    "time": "20:00:00",
    "counts": {
      "requests": 16658,
      "allowedrequests": 16327,
      "blockedrequests": 331,
      "connectedevents": 0,
      "disconnectedevents": 0
    }
  },
  {
    "count": 15737,
    "timestamp": 1775250000000,
    "date": "2026-04-03",
    "time": "21:00:00",
    "counts": {
      "requests": 15737,
      "allowedrequests": 15496,
      "blockedrequests": 241,
      "connectedevents": 0,
      "disconnectedevents": 0
    }
  },
  {
    "count": 18363,
    "timestamp": 1775253600000,
    "date": "2026-04-03",
    "time": "22:00:00",
    "counts": {
      "requests": 18363,
      "allowedrequests": 18079,
      "blockedrequests": 284,
      "connectedevents": 0,
      "disconnectedevents": 0
    }
  },
  {
    "count": 18238,
    "timestamp": 1775257200000,
    "date": "2026-04-03",
    "time": "23:00:00",
    "counts": {
      "requests": 18238,
      "allowedrequests": 17820,
      "blockedrequests": 418,
      "connectedevents": 0,
      "disconnectedevents": 0
    }
  }
]