<Root><Invoice><InvoiceID>43926</InvoiceID><InvoiceNo>26548</InvoiceNo><DueDate>2025-10-01</DueDate><InvoiceDate>2025-09-01</InvoiceDate><Paid>0.0000</Paid><Total>0.0000</Total><InvoiceType>Monthly</InvoiceType><Status>Void</Status><Title>JSD : Monthly Invoice for DKIM+Site Assessment</Title></Invoice><Invoice><InvoiceID>43686</InvoiceID><InvoiceNo>26224</InvoiceNo><DueDate>2025-08-31</DueDate><InvoiceDate>2025-08-01</InvoiceDate><Paid>0.0000</Paid><Total>0.0000</Total><InvoiceType>Monthly</InvoiceType><Status>Void</Status><Title>JSD : Monthly Invoice for DKIM+Site Assessment</Title></Invoice><Invoice><InvoiceID>43425</InvoiceID><InvoiceNo>25972</InvoiceNo><DueDate>2025-07-31</DueDate><InvoiceDate>2025-07-01</InvoiceDate><Paid>70.0000</Paid><Total>70.0000</Total><InvoiceType>Monthly</InvoiceType><Status>Paid</Status><PaymentDate>2025-07-11</PaymentDate><Title>JSD : Monthly Invoice for DKIM+Site Assessment</Title></Invoice><Invoice><InvoiceID>43205</InvoiceID><InvoiceNo>25744</InvoiceNo><DueDate>2025-07-01</DueDate><InvoiceDate>2025-06-01</InvoiceDate><Paid>70.0000</Paid><Total>70.0000</Total><InvoiceType>Monthly</InvoiceType><Status>Paid</Status><PaymentDate>2025-07-11</PaymentDate><Title>JSD : Monthly Invoice for DKIM+Site Assessment</Title></Invoice><Invoice><InvoiceID>42665</InvoiceID><InvoiceNo>25426</InvoiceNo><DueDate>2025-05-31</DueDate><InvoiceDate>2025-05-01</InvoiceDate><Paid>70.0000</Paid><Total>70.0000</Total><InvoiceType>Monthly</InvoiceType><Status>Paid</Status><PaymentDate>2025-06-04</PaymentDate><Title>JSD : Monthly Invoice for DKIM+Site Assessment</Title></Invoice><Invoice><InvoiceID>42811</InvoiceID><InvoiceNo>25325</InvoiceNo><DueDate>2025-05-11</DueDate><InvoiceDate>2025-04-11</InvoiceDate><Paid>0.0000</Paid><Total>0.0000</Total><InvoiceType>Weekly</InvoiceType><Status>Paid</Status><Title>Weekly Invoice</Title></Invoice><Invoice><InvoiceID>42663</InvoiceID><InvoiceNo>25208</InvoiceNo><DueDate>2025-05-02</DueDate><InvoiceDate>2025-04-02</InvoiceDate><Paid>5796.0000</Paid><Total>5796.0000</Total><InvoiceType>Invoice</InvoiceType><Status>Paid</Status><PaymentDate>2025-04-02</PaymentDate><Title>Hourly Support Retainer</Title></Invoice><Invoice><InvoiceID>42664</InvoiceID><InvoiceNo>25210</InvoiceNo><DueDate>2025-04-02</DueDate><InvoiceDate>2025-04-01</InvoiceDate><Paid>72.4500</Paid><Total>72.4500</Total><InvoiceType>Monthly</InvoiceType><Status>Paid</Status><PaymentDate>2025-04-02</PaymentDate><Title>JSD : Monthly Invoice for DKIM+Site Assessment</Title></Invoice></Root>