[
  {
    "number": 5,
    "enabled": false,
    "dropUntaggedTraffic": true,
    "type": "trunk",
    "allowedVlans": "all"
  },
  {
    "number": 6,
    "enabled": false,
    "dropUntaggedTraffic": true,
    "type": "trunk",
    "allowedVlans": "all"
  },
  {
    "number": 7,
    "enabled": false,
    "dropUntaggedTraffic": true,
    "type": "trunk",
    "allowedVlans": "all"
  },
  {
    "number": 8,
    "enabled": false,
    "dropUntaggedTraffic": true,
    "type": "trunk",
    "allowedVlans": "all"
  },
  {
    "number": 9,
    "enabled": false,
    "dropUntaggedTraffic": true,
    "type": "trunk",
    "allowedVlans": "all"
  },
  {
    "number": 10,
    "enabled": true,
    "type": "trunk",
    "dropUntaggedTraffic": false,
    "vlan": 49,
    "allowedVlans": "all"
  }
]