[
  {
    "RESOURCE_ID": 323741,
    "resource_name": "VG-DC-3CX-02",
    "PATCH_ID": 356165,
    "PATCHNAME": "googlechromestandaloneenterprise64_145.0.7632.110.msi",
    "BULLETINID": "TU-017",
    "SEVERITYID": 3,
    "SUPERCEDEDBY": "356345",
    "INSTALLED_TIME": 1771650295000,
    "DEPLOY_STATUS": 2,
    "DEPLOY_STATUS_ID": 209,
    "ERROR_CODE": -1
  },
  {
    "RESOURCE_ID": 323741,
    "resource_name": "VG-DC-3CX-02",
    "PATCH_ID": 355986,
    "PATCHNAME": "googlechromestandaloneenterprise64_145.0.7632.68.msi",
    "BULLETINID": "TU-017",
    "SEVERITYID": 3,
    "SUPERCEDEDBY": "356041",
    "INSTALLED_TIME": 1771047532000,
    "DEPLOY_STATUS": 2,
    "DEPLOY_STATUS_ID": 209,
    "ERROR_CODE": -1
  },
  {
    "RESOURCE_ID": 323741,
    "resource_name": "VG-DC-3CX-02",
    "PATCH_ID": 43411,
    "PATCHNAME": "windows-kb890830-x64-v5-139.exe",
    "BULLETINID": "MSRT-001",
    "SEVERITYID": 2,
    "SUPERCEDEDBY": "44036",
    "INSTALLED_TIME": 1771047405000,
    "DEPLOY_STATUS": 2,
    "DEPLOY_STATUS_ID": 209,
    "ERROR_CODE": -1
  },
  {
    "RESOURCE_ID": 323741,
    "resource_name": "VG-DC-3CX-02",
    "PATCH_ID": 354955,
    "PATCHNAME": "googlechromestandaloneenterprise64_144.0.7559.60.msi",
    "BULLETINID": "TU-017",
    "SEVERITYID": 3,
    "SUPERCEDEDBY": "355150",
    "INSTALLED_TIME": 1768626738000,
    "DEPLOY_STATUS": 2,
    "DEPLOY_STATUS_ID": 209,
    "ERROR_CODE": -1
  },
  {
    "RESOURCE_ID": 323741,
    "resource_name": "VG-DC-3CX-02",
    "PATCH_ID": 354427,
    "PATCHNAME": "googlechromestandaloneenterprise64_143.0.7499.170.msi",
    "BULLETINID": "TU-017",
    "SEVERITYID": 3,
    "SUPERCEDEDBY": "354769",
    "INSTALLED_TIME": 1766206988000,
    "DEPLOY_STATUS": 2,
    "DEPLOY_STATUS_ID": 209,
    "ERROR_CODE": -1
  },
  {
    "RESOURCE_ID": 323741,
    "resource_name": "VG-DC-3CX-02",
    "PATCH_ID": 354150,
    "PATCHNAME": "googlechromestandaloneenterprise64_143.0.7499.110.msi",
    "BULLETINID": "TU-017",
    "SEVERITYID": 3,
    "SUPERCEDEDBY": "354329",
    "INSTALLED_TIME": 1765603707000,
    "DEPLOY_STATUS": 2,
    "DEPLOY_STATUS_ID": 209,
    "ERROR_CODE": -1
  },
  {
    "RESOURCE_ID": 323741,
    "resource_name": "VG-DC-3CX-02",
    "PATCH_ID": 43162,
    "PATCHNAME": "microsoftedgeenterprise_143.0.3650.80_x64.msi",
    "BULLETINID": "MS22-EDGE",
    "SEVERITYID": 2,
    "SUPERCEDEDBY": "43181",
    "INSTALLED_TIME": 1765603618000,
    "DEPLOY_STATUS": 2,
    "DEPLOY_STATUS_ID": 209,
    "ERROR_CODE": -1
  },
  {
    "RESOURCE_ID": 323741,
    "resource_name": "VG-DC-3CX-02",
    "PATCH_ID": 43089,
    "PATCHNAME": "Windows-kb890830-x64-v5.138.exe",
    "BULLETINID": "MSRT-001",
    "SEVERITYID": 2,
    "SUPERCEDEDBY": "43411",
    "INSTALLED_TIME": 1765603488000,
    "DEPLOY_STATUS": 2,
    "DEPLOY_STATUS_ID": 209,
    "ERROR_CODE": -1
  },
  {
    "RESOURCE_ID": 323741,
    "resource_name": "VG-DC-3CX-02",
    "PATCH_ID": 43070,
    "PATCHNAME": "windows10.0-kb5071547-x64-2022.msu",
    "BULLETINID": "MS25-DEC3",
    "SEVERITYID": 4,
    "SUPERCEDEDBY": "43211",
    "INSTALLED_TIME": 1765602188000,
    "DEPLOY_STATUS": 2,
    "DEPLOY_STATUS_ID": 209,
    "ERROR_CODE": -1
  },
  {
    "RESOURCE_ID": 323741,
    "resource_name": "VG-DC-3CX-02",
    "PATCH_ID": 353852,
    "PATCHNAME": "googlechromestandaloneenterprise64_143.0.7499.41.msi",
    "BULLETINID": "TU-017",
    "SEVERITYID": 3,
    "SUPERCEDEDBY": "354150",
    "INSTALLED_TIME": 1764997572000,
    "DEPLOY_STATUS": 2,
    "DEPLOY_STATUS_ID": 209,
    "ERROR_CODE": -1
  },
  {
    "RESOURCE_ID": 323741,
    "resource_name": "VG-DC-3CX-02",
    "PATCH_ID": 112875,
    "PATCHNAME": "MicrosoftEdgeWebView2RuntimeInstallerX64_143.0.3650.66.exe",
    "BULLETINID": "MSWU-3507",
    "SEVERITYID": 0,
    "SUPERCEDEDBY": "112893",
    "INSTALLED_TIME": 1764997505000,
    "DEPLOY_STATUS": 2,
    "DEPLOY_STATUS_ID": 209,
    "ERROR_CODE": -1
  },
  {
    "RESOURCE_ID": 323741,
    "resource_name": "VG-DC-3CX-02",
    "PATCH_ID": 43061,
    "PATCHNAME": "microsoftedgeenterprise_143.0.3650.66_x64.msi",
    "BULLETINID": "MS22-EDGE",
    "SEVERITYID": 3,
    "SUPERCEDEDBY": "112891",
    "INSTALLED_TIME": 1764997392000,
    "DEPLOY_STATUS": 2,
    "DEPLOY_STATUS_ID": 209,
    "ERROR_CODE": -1
  },
  {
    "RESOURCE_ID": 323741,
    "resource_name": "VG-DC-3CX-02",
    "PATCH_ID": 112860,
    "PATCHNAME": "MicrosoftEdgeWebView2RuntimeInstallerX64_142.0.3595.94.exe",
    "BULLETINID": "MSWU-3507",
    "SEVERITYID": 0,
    "SUPERCEDEDBY": "112875",
    "INSTALLED_TIME": 1763787886000,
    "DEPLOY_STATUS": 2,
    "DEPLOY_STATUS_ID": 209,
    "ERROR_CODE": -1
  },
  {
    "RESOURCE_ID": 323741,
    "resource_name": "VG-DC-3CX-02",
    "PATCH_ID": 112858,
    "PATCHNAME": "microsoftedgeenterprise_142.0.3595.94_x64.msi",
    "BULLETINID": "MSWU-3491",
    "SEVERITYID": 2,
    "SUPERCEDEDBY": "43061",
    "INSTALLED_TIME": 1763787786000,
    "DEPLOY_STATUS": 2,
    "DEPLOY_STATUS_ID": 209,
    "ERROR_CODE": -1
  },
  {
    "RESOURCE_ID": 323741,
    "resource_name": "VG-DC-3CX-02",
    "PATCH_ID": 353232,
    "PATCHNAME": "googlechromestandaloneenterprise64_142.0.7444.163.msi",
    "BULLETINID": "TU-017",
    "SEVERITYID": 3,
    "SUPERCEDEDBY": "353434",
    "INSTALLED_TIME": 1763184521000,
    "DEPLOY_STATUS": 2,
    "DEPLOY_STATUS_ID": 209,
    "ERROR_CODE": -1
  },
  {
    "RESOURCE_ID": 323741,
    "resource_name": "VG-DC-3CX-02",
    "PATCH_ID": 112835,
    "PATCHNAME": "VC_redist.x64__14.50.35710.0.exe",
    "BULLETINID": "MSWU-3550",
    "SEVERITYID": 0,
    "SUPERCEDEDBY": "112862",
    "INSTALLED_TIME": 1763184511000,
    "DEPLOY_STATUS": 2,
    "DEPLOY_STATUS_ID": 209,
    "ERROR_CODE": -1
  },
  {
    "RESOURCE_ID": 323741,
    "resource_name": "VG-DC-3CX-02",
    "PATCH_ID": 112834,
    "PATCHNAME": "VC_redist.x86__14.50.35710.0.exe",
    "BULLETINID": "MSWU-3550",
    "SEVERITYID": 0,
    "SUPERCEDEDBY": "112861",
    "INSTALLED_TIME": 1763184503000,
    "DEPLOY_STATUS": 2,
    "DEPLOY_STATUS_ID": 209,
    "ERROR_CODE": -1
  },
  {
    "RESOURCE_ID": 323741,
    "resource_name": "VG-DC-3CX-02",
    "PATCH_ID": 43005,
    "PATCHNAME": "microsoftedgeenterprise_142.0.3595.80_x64.msi",
    "BULLETINID": "MS22-EDGE",
    "SEVERITYID": 3,
    "SUPERCEDEDBY": "43025",
    "INSTALLED_TIME": 1763184418000,
    "DEPLOY_STATUS": 2,
    "DEPLOY_STATUS_ID": 209,
    "ERROR_CODE": -1
  },
  {
    "RESOURCE_ID": 323741,
    "resource_name": "VG-DC-3CX-02",
    "PATCH_ID": 42904,
    "PATCHNAME": "windows-kb890830-x64-v5.137.exe",
    "BULLETINID": "MSRT-001",
    "SEVERITYID": 2,
    "SUPERCEDEDBY": "43089",
    "INSTALLED_TIME": 1763184295000,
    "DEPLOY_STATUS": 2,
    "DEPLOY_STATUS_ID": 209,
    "ERROR_CODE": -1
  },
  {
    "RESOURCE_ID": 323741,
    "resource_name": "VG-DC-3CX-02",
    "PATCH_ID": 42885,
    "PATCHNAME": "Windows10.0-kb5068787-x64-2022.msu",
    "BULLETINID": "MS25-NOV3",
    "SEVERITYID": 4,
    "SUPERCEDEDBY": "43070",
    "INSTALLED_TIME": 1763182986000,
    "DEPLOY_STATUS": 2,
    "DEPLOY_STATUS_ID": 209,
    "ERROR_CODE": -1
  },
  {
    "RESOURCE_ID": 323741,
    "resource_name": "VG-DC-3CX-02",
    "PATCH_ID": 353092,
    "PATCHNAME": "googlechromestandaloneenterprise64_142.0.7444.135.msi",
    "BULLETINID": "TU-017",
    "SEVERITYID": 3,
    "SUPERCEDEDBY": "353232",
    "INSTALLED_TIME": 1762578342000,
    "DEPLOY_STATUS": 2,
    "DEPLOY_STATUS_ID": 209,
    "ERROR_CODE": -1
  },
  {
    "RESOURCE_ID": 323741,
    "resource_name": "VG-DC-3CX-02",
    "PATCH_ID": 112819,
    "PATCHNAME": "MicrosoftEdgeWebView2RuntimeInstallerX64_142.0.3595.65.exe",
    "BULLETINID": "MSWU-3507",
    "SEVERITYID": 0,
    "SUPERCEDEDBY": "112823",
    "INSTALLED_TIME": 1762578286000,
    "DEPLOY_STATUS": 2,
    "DEPLOY_STATUS_ID": 209,
    "ERROR_CODE": -1
  },
  {
    "RESOURCE_ID": 323741,
    "resource_name": "VG-DC-3CX-02",
    "PATCH_ID": 42868,
    "PATCHNAME": "microsoftedgeenterprise_142.0.3595.65_x64.msi",
    "BULLETINID": "MS22-EDGE",
    "SEVERITYID": 3,
    "SUPERCEDEDBY": "112821",
    "INSTALLED_TIME": 1762578185000,
    "DEPLOY_STATUS": 2,
    "DEPLOY_STATUS_ID": 209,
    "ERROR_CODE": -1
  },
  {
    "RESOURCE_ID": 323741,
    "resource_name": "VG-DC-3CX-02",
    "PATCH_ID": 352865,
    "PATCHNAME": "googlechromestandaloneenterprise64_142.0.7444.60.msi",
    "BULLETINID": "TU-017",
    "SEVERITYID": 3,
    "SUPERCEDEDBY": "353092",
    "INSTALLED_TIME": 1761969785000,
    "DEPLOY_STATUS": 2,
    "DEPLOY_STATUS_ID": 209,
    "ERROR_CODE": -1
  },
  {
    "RESOURCE_ID": 323741,
    "resource_name": "VG-DC-3CX-02",
    "PATCH_ID": 42827,
    "PATCHNAME": "Windows10.0-kb5070884-x64-2022.msu",
    "BULLETINID": "MS25-OCT18",
    "SEVERITYID": 4,
    "SUPERCEDEDBY": "42885",
    "INSTALLED_TIME": 1761364983000,
    "DEPLOY_STATUS": 2,
    "DEPLOY_STATUS_ID": 209,
    "ERROR_CODE": -1
  },
  {
    "RESOURCE_ID": 323741,
    "resource_name": "VG-DC-3CX-02",
    "PATCH_ID": 42686,
    "PATCHNAME": "windows-kb890830-x64-v5.136.exe",
    "BULLETINID": "MSRT-001",
    "SEVERITYID": 2,
    "SUPERCEDEDBY": "42904",
    "INSTALLED_TIME": 1760761691000,
    "DEPLOY_STATUS": 2,
    "DEPLOY_STATUS_ID": 209,
    "ERROR_CODE": -1
  },
  {
    "RESOURCE_ID": 323741,
    "resource_name": "VG-DC-3CX-02",
    "PATCH_ID": 42663,
    "PATCHNAME": "Windows10.0-kb5066782-x64-2022.msu",
    "BULLETINID": "MS25-OCT3",
    "SEVERITYID": 4,
    "SUPERCEDEDBY": "42827",
    "INSTALLED_TIME": 1760760182000,
    "DEPLOY_STATUS": 2,
    "DEPLOY_STATUS_ID": 209,
    "ERROR_CODE": -1
  },
  {
    "RESOURCE_ID": 323741,
    "resource_name": "VG-DC-3CX-02",
    "PATCH_ID": 112546,
    "PATCHNAME": "VC_redist.x64__14.44.35211.0.exe",
    "BULLETINID": "MSWU-3550",
    "SEVERITYID": 0,
    "SUPERCEDEDBY": "112835",
    "INSTALLED_TIME": 1760241800000,
    "DEPLOY_STATUS": 2,
    "DEPLOY_STATUS_ID": 209,
    "ERROR_CODE": -1
  },
  {
    "RESOURCE_ID": 323741,
    "resource_name": "VG-DC-3CX-02",
    "PATCH_ID": 112545,
    "PATCHNAME": "VC_redist.x86__14.44.35211.0.exe",
    "BULLETINID": "MSWU-3550",
    "SEVERITYID": 0,
    "SUPERCEDEDBY": "112834",
    "INSTALLED_TIME": 1760241792000,
    "DEPLOY_STATUS": 2,
    "DEPLOY_STATUS_ID": 209,
    "ERROR_CODE": -1
  }
]